odoo/addons/sale_layout_category_hide_detail/README.rst
odoo/addons/sale_layout_category_hide_detail/__init__.py
odoo/addons/sale_layout_category_hide_detail/__manifest__.py
odoo/addons/sale_layout_category_hide_detail/i18n/es.po
odoo/addons/sale_layout_category_hide_detail/i18n/fr.po
odoo/addons/sale_layout_category_hide_detail/i18n/it.po
odoo/addons/sale_layout_category_hide_detail/i18n/pt_BR.po
odoo/addons/sale_layout_category_hide_detail/i18n/sale_layout_category_hide_detail.pot
odoo/addons/sale_layout_category_hide_detail/models/__init__.py
odoo/addons/sale_layout_category_hide_detail/models/account_move.py
odoo/addons/sale_layout_category_hide_detail/models/sale_order.py
odoo/addons/sale_layout_category_hide_detail/readme/CONTRIBUTORS.md
odoo/addons/sale_layout_category_hide_detail/readme/DESCRIPTION.md
odoo/addons/sale_layout_category_hide_detail/readme/ROADMAP.md
odoo/addons/sale_layout_category_hide_detail/readme/USAGE.md
odoo/addons/sale_layout_category_hide_detail/static/description/icon.png
odoo/addons/sale_layout_category_hide_detail/static/description/index.html
odoo/addons/sale_layout_category_hide_detail/static/description/readme-icons/eye-slash.png
odoo/addons/sale_layout_category_hide_detail/static/description/readme-icons/eye.png
odoo/addons/sale_layout_category_hide_detail/static/description/readme-icons/minus-circle.png
odoo/addons/sale_layout_category_hide_detail/static/description/readme-icons/order.png
odoo/addons/sale_layout_category_hide_detail/static/description/readme-icons/plus-circle.png
odoo/addons/sale_layout_category_hide_detail/static/description/readme-icons/report.png
odoo/addons/sale_layout_category_hide_detail/static/src/js/boolean_fa_icon_widget.esm.js
odoo/addons/sale_layout_category_hide_detail/static/src/js/sale_layout_category_hide_detail.esm.js
odoo/addons/sale_layout_category_hide_detail/static/src/xml/boolean_fa_icon_widget.xml
odoo/addons/sale_layout_category_hide_detail/tests/__init__.py
odoo_addon_sale_layout_category_hide_detail-18.0.1.0.0.2.dist-info/METADATA
odoo_addon_sale_layout_category_hide_detail-18.0.1.0.0.2.dist-info/WHEEL
odoo_addon_sale_layout_category_hide_detail-18.0.1.0.0.2.dist-info/top_level.txt
odoo_addon_sale_layout_category_hide_detail-18.0.1.0.0.2.dist-info/RECORD
